file_healthchecker/__init__.py
file_healthchecker/entrypoint.py
file_healthchecker-0.1.1.dist-info/LICENSE
file_healthchecker-0.1.1.dist-info/METADATA
file_healthchecker-0.1.1.dist-info/WHEEL
file_healthchecker-0.1.1.dist-info/entry_points.txt
file_healthchecker-0.1.1.dist-info/top_level.txt
file_healthchecker-0.1.1.dist-info/RECORD
