Metadata-Version: 2.1
Name: file-healthchecker
Version: 0.1.1
Summary: Check health of static, long running applications using generated files.
Home-page: UNKNOWN
Author: Ankur Srivastava
Author-email: ankur.srivastava@email.de
License: UNKNOWN
Download-URL: https://github.com/ansrivas/healthchecker/0.1.1.tar.gz
Platform: UNKNOWN
Classifier: Programming Language :: Python :: 3
Classifier: Programming Language :: Python :: 3.6
Classifier: Programming Language :: Python :: 3.7
Classifier: Programming Language :: Python :: 3.8
Requires-Python: >=3.6.0
Provides-Extra: dev
Requires-Dist: python-language-server[all] ; extra == 'dev'
Requires-Dist: black (==19.3b0) ; extra == 'dev'
Provides-Extra: test
Requires-Dist: pytest (==5.2.1) ; extra == 'test'
Requires-Dist: pytest-sugar (==0.9.2) ; extra == 'test'
Requires-Dist: pytest-asyncio (==0.10.0) ; extra == 'test'
Requires-Dist: pytest-cov (==2.8.1) ; extra == 'test'
